inch/__init__.py
inch/__main__.py
inch/async_example.py
inch/core.py
inch/executor.py
inch/func_inch.py
inch/py.typed
inch/processor/__init__.py
inch/processor/async_executor.py
inch/processor/async_func_inch.py
inch/processor/async_inch.py
inch/processor/inch_processor.py
inch/processor/logger.py
inch/type/__init__.py
inch-0.2.0.dist-info/METADATA
inch-0.2.0.dist-info/WHEEL
inch-0.2.0.dist-info/RECORD
