Metadata-Version: 2.4
Name: inch
Version: 0.2.0
Summary: A Python library for managing and executing long-running tasks in batches with visual progress tracking
Project-URL: Homepage, https://github.com/jannchie/inch
Project-URL: Documentation, https://github.com/jannchie/inch#readme
Project-URL: Bug Tracker, https://github.com/jannchie/inch/issues
Author-email: Jianqi Pan <jannchie@gmail.com>
License: MIT
Keywords: batch-processing,cli,concurrency,multithreading,progress
Classifier: Development Status :: 4 - Beta
Classifier: Intended Audience :: Developers
Classifier: Programming Language :: Python :: 3
Classifier: Programming Language :: Python :: 3.10
Classifier: Programming Language :: Python :: 3.11
Classifier: Programming Language :: Python :: 3.12
Classifier: Programming Language :: Python :: 3.13
Classifier: Topic :: Software Development :: Libraries
Classifier: Topic :: Utilities
Requires-Python: >=3.10
Requires-Dist: rich>=13.9.2
